ragdata/__init__.py
ragdata/base.py
ragdata/arxiv/__init__.py
ragdata/arxiv/index.py
ragdata/wikipedia/__init__.py
ragdata/wikipedia/index.py
ragdata/wikipedia/views.py
ragdata-0.3.0.dist-info/LICENSE
ragdata-0.3.0.dist-info/METADATA
ragdata-0.3.0.dist-info/WHEEL
ragdata-0.3.0.dist-info/top_level.txt
ragdata-0.3.0.dist-info/RECORD
