Metadata-Version: 2.1
Name: ragdata
Version: 0.3.0
Summary: Build knowledge bases for RAG
Home-page: https://github.com/neuml/ragdata
Author: NeuML
License: Apache 2.0: http://www.apache.org/licenses/LICENSE-2.0
Project-URL: Documentation, https://github.com/neuml/ragdata
Project-URL: Issue Tracker, https://github.com/neuml/ragdata/issues
Project-URL: Source Code, https://github.com/neuml/ragdata
Keywords: search embedding machine-learning nlp
Classifier: License :: OSI Approved :: Apache Software License
Classifier: Operating System :: OS Independent
Classifier: Programming Language :: Python :: 3
Classifier: Topic :: Scientific/Engineering :: Artificial Intelligence
Classifier: Topic :: Software Development
Classifier: Topic :: Text Processing :: Indexing
Classifier: Topic :: Utilities
Requires-Python: >=3.10
License-File: LICENSE
Requires-Dist: datasets >=3.0.1
Requires-Dist: nltk >=3.5
Requires-Dist: pandas >=1.3.5
Requires-Dist: tqdm >=4.48.0
Requires-Dist: txtai >=8.5.0
